{
  "type": "minecraft:entity",
  "pools": [
    {
      "rolls": 1,
      "entries": [
        {
          "type": "minecraft:item",
          "name": "minecraft:string"
        }
      ],
      "conditions": [
        {
          "condition": "random_chance",
          "chance": 0.6
        }
      ]
    },
    {
      "rolls": 1,
      "entries": [
        {
          "type": "minecraft:item",
          "name": "minecraft:string"
        }
      ],
      "conditions": [
        {
          "condition": "random_chance_with_enchanted_bonus",
          "unenchanted_chance": 0.15,
          "enchanted_chance": {
            "type": "minecraft:linear",
            "base": 0.25,
            "per_level_above_first": 0.1
          },
          "enchantment": "minecraft:looting"
        }
      ]
    },
    {
      "rolls": 1,
      "entries": [
        {
          "type": "minecraft:item",
          "name": "minecraft:string"
        }
      ],
      "conditions": [
        {
          "condition": "random_chance_with_enchanted_bonus",
          "unenchanted_chance": 0,
          "enchanted_chance": {
            "type": "minecraft:linear",
            "base": 0.05,
            "per_level_above_first": 0.05
          },
          "enchantment": "minecraft:looting"
        }
      ]
    },
    {
      "rolls": 1,
      "entries": [
        {
          "type": "minecraft:item",
          "name": "minecraft:spider_eye"
        }
      ],
      "conditions": [
        {
          "condition": "random_chance",
          "chance": 0.3
        }
      ]
    },
    {
      "rolls": 1,
      "entries": [
        {
          "type": "minecraft:item",
          "name": "minecraft:spider_eye"
        }
      ],
      "conditions": [
        {
          "condition": "random_chance_with_enchanted_bonus",
          "unenchanted_chance": 0.1,
          "enchanted_chance": {
            "type": "minecraft:linear",
            "base": 0.3,
            "per_level_above_first": 0.2
          },
          "enchantment": "minecraft:looting"
        }
      ]
    },
    {
      "rolls": 1,
      "entries": [
        {
          "type": "minecraft:item",
          "name": "minecraft:spider_eye"
        }
      ],
      "conditions": [
        {
          "condition": "random_chance_with_enchanted_bonus",
          "unenchanted_chance": 0.05,
          "enchanted_chance": {
            "type": "minecraft:linear",
            "base": 0.15,
            "per_level_above_first": 0.1
          },
          "enchantment": "minecraft:looting"
        }
      ]
    },
    {
      "rolls": 1,
      "entries": [
        {
          "type": "minecraft:item",
          "name": "minecraft:cobweb"
        }
      ],
      "conditions": [
        {
          "condition": "random_chance_with_enchanted_bonus",
          "unenchanted_chance": 0,
          "enchanted_chance": {
            "type": "minecraft:linear",
            "base": 0.025,
            "per_level_above_first": 0.025
          },
          "enchantment": "minecraft:looting"
        }
      ]
    }
  ]
}
